pyp_beagle/__init__.py
pyp_beagle/_version.py
pyp_beagle/beagle_calibration_correction.py
pyp_beagle/beagle_filters.py
pyp_beagle/beagle_mock_catalogue.py
pyp_beagle/beagle_multinest_catalogue.py
pyp_beagle/beagle_multiprocess.py
pyp_beagle/beagle_observed_catalogue.py
pyp_beagle/beagle_parsers.py
pyp_beagle/beagle_pdf.py
pyp_beagle/beagle_photometry.py
pyp_beagle/beagle_posterior_predictive_checks.py
pyp_beagle/beagle_residual_photometry.py
pyp_beagle/beagle_spectra.py
pyp_beagle/beagle_spectral_indices.py
pyp_beagle/beagle_summary_catalogue.py
pyp_beagle/beagle_utils.py
pyp_beagle/command_line.py
pyp_beagle/conftest.py
pyp_beagle/significant_digits.py
pyp_beagle/dependencies/FillBetweenStep.py
pyp_beagle/dependencies/WeightedKDE.py
pyp_beagle/dependencies/__init__.py
pyp_beagle/dependencies/autoscale.py
pyp_beagle/dependencies/set_shared_labels.py
pyp_beagle/dependencies/walker_random_sampling.py
pyp_beagle/files/calibration_correction.json
pyp_beagle/files/emission_lines.json
pyp_beagle/files/params_names.json
pyp_beagle/files/params_names_latex_table.json
pyp_beagle/files/params_names_mock.json
pyp_beagle/files/summary_config.json
pyp_beagle-0.10.23.dist-info/METADATA
pyp_beagle-0.10.23.dist-info/WHEEL
pyp_beagle-0.10.23.dist-info/entry_points.txt
pyp_beagle-0.10.23.dist-info/top_level.txt
pyp_beagle-0.10.23.dist-info/RECORD
