Metadata-Version: 2.1
Name: pyp-beagle
Version: 0.10.23
Summary: Package for post-processing of results obtained with the Beagle SED fitting tool
Home-page: https://github.com/jacopo-chevallard/PyP-BEAGLE
Author: Jacopo Chevallard
Author-email: jacopo.chevallard@mailfence.com
License: MIT
Keywords: astronomy galaxies statistics visualization
Platform: UNKNOWN
Classifier: Development Status :: 3 - Alpha
Classifier: Intended Audience :: Science/Research
Classifier: Topic :: Scientific/Engineering :: Astronomy
Classifier: License :: OSI Approved :: MIT License
Classifier: Programming Language :: Python :: 3.8
Requires-Dist: matplotlib
Requires-Dist: scipy
Requires-Dist: numpy
Requires-Dist: getdist
Requires-Dist: pathos
Requires-Dist: extension-helpers
Requires-Dist: astropy
Requires-Dist: bokeh
Requires-Dist: natsort
Requires-Dist: six
